entanglement_temp_controller/__init__.py
entanglement_temp_controller/__main__.py
entanglement_temp_controller/main.py
entanglement_temp_controller/static/favicon.ico
entanglement_temp_controller/static/logo.svg
entanglement_temp_controller/static/style.css
entanglement_temp_controller/static/white_logo.png
entanglement_temp_controller/tc720/__init__.py
entanglement_temp_controller/tc720/cli.py
entanglement_temp_controller/tc720/controller.py
entanglement_temp_controller/tc720/devices.py
entanglement_temp_controller/tc720/mock_controller.py
entanglement_temp_controller/templates/contact.html
entanglement_temp_controller/templates/index.html
entanglement_temp_controller-1.0.5.dist-info/METADATA
entanglement_temp_controller-1.0.5.dist-info/WHEEL
entanglement_temp_controller-1.0.5.dist-info/entry_points.txt
entanglement_temp_controller-1.0.5.dist-info/top_level.txt
entanglement_temp_controller-1.0.5.dist-info/RECORD
