Metadata-Version: 2.4
Name: entanglement-temp-controller
Version: 1.0.5
Summary: Flask based temperature controller for serial devices
Author: Quantum Computing Inc.
Author-email: support@quantumcomputinginc.com
License: Apache 2.0
Requires-Python: >=3.9
Requires-Dist: requests
Requires-Dist: uvicorn
Requires-Dist: fastapi
Requires-Dist: pyserial
Requires-Dist: flask
